fast_histogram/__init__.py
fast_histogram/_histogram_core.pyd
fast_histogram/histogram.py
fast_histogram/version.py
fast_histogram/tests/__init__.py
fast_histogram/tests/test_histogram.py
fast_histogram-0.14.dist-info/LICENSE
fast_histogram-0.14.dist-info/METADATA
fast_histogram-0.14.dist-info/WHEEL
fast_histogram-0.14.dist-info/top_level.txt
fast_histogram-0.14.dist-info/RECORD
