Metadata-Version: 2.1
Name: fast-histogram
Version: 0.14
Summary: Fast simple 1D and 2D histograms
Home-page: https://github.com/astrofrog/fast-histogram
Author: Thomas Robitaille
Author-email: thomas.robitaille@gmail.com
License: BSD
Requires-Python: >=3.9
License-File: LICENSE
Requires-Dist: numpy
Provides-Extra: test
Requires-Dist: pytest ; extra == 'test'
Requires-Dist: hypothesis[numpy] ; extra == 'test'
